{"Data":{"attr":{"Data":[{"arabic":"Null","atr":"Null","color":"#55FFD4"},{"arabic":"لازم","atr":"F.L","color":"#548DD4"},{"arabic":"لازم و متعدي","atr":"F. LM","color":"#AD2323"},{"arabic":"متعدي","atr":"F. M","color":"#575757"},{"arabic":"مبهم","atr":"M","color":"#575757"},{"arabic":"ادات استثناء","atr":"A.ES","color":"#32BD2F"},{"arabic":"ادات تاکيد","atr":"A.TA","color":"#A8017B"},{"arabic":"اسم آلت","atr":"E.AL","color":"#1301B8"},{"arabic":"اسم استفهام","atr":"E.ES","color":"#F4400B"},{"arabic":"اسم اشاره","atr":"E.ESH","color":"#BF9F3E"},{"arabic":"اسم تفضيل","atr":"E.TF","color":"#E11010"},{"arabic":"اسم تفضيل","atr":"E.TF","color":"#A8017B"},{"arabic":"اسم جامد","atr":"E.JA","color":"#548DD4"},{"arabic":"اسم زمان و مکان","atr":"E.ZM","color":"#AD2323"},{"arabic":"اسم شرط","atr":"E.SH","color":"#E11010"},{"arabic":"اسم فاعل","atr":"E.FAL  ","color":"#2D839F"},{"arabic":"اسم فعل","atr":"E.F","color":"#0000FF"},{"arabic":"اسم مفعول","atr":"E.MA","color":"#F4400B"},{"arabic":"جامد غير مصدري","atr":"J.QM","color":"#BF9F3E"},{"arabic":"صفت مشبهه","atr":"E.SM","color":"#A8017B"},{"arabic":"صيغه مبالغه","atr":"E.SMO","color":"#548DD4"},{"arabic":"ضمير متصل","atr":"E.ZT","color":"#445706"},{"arabic":"ضمير منفصل","atr":"E.ZN","color":"#1126C0"},{"arabic":"ظرف","atr":"E.ZR","color":"#8126C0"},{"arabic":"مصدر","atr":"E.MS","color":"#2D839F"},{"arabic":"مصدر ميمي","atr":"E.MM","color":"#32BD2F"},{"arabic":"موصول","atr":"E.MO","color":"#817418"},{"arabic":"مبهم","atr":"M","color":"#1301B8"},{"arabic":"ابتدائيّة","atr":"EB","color":"#F4400B"},{"arabic":"ادات استثناء","atr":"BG","color":"#F4400B"},{"arabic":"ادات حصر","atr":"H.HS","color":"#2AAAFF"},{"arabic":"استفتاحية","atr":"H.ET","color":"#F4400B"},{"arabic":"استفهاميّة","atr":"H.ES","color":"#2AAAFF"},{"arabic":"استينافيّة","atr":"H.EN","color":"#F4400B"},{"arabic":"اضراب","atr":"H.EZ","color":"#7A57BB"},{"arabic":"امتناعيّة","atr":"H.EM","color":"#E11010"},{"arabic":"تحقيقيّة","atr":"H.TH","color":"#F4400B"},{"arabic":"تعريف","atr":"H.TR","color":"#A8017B"},{"arabic":"تعليلية","atr":"H.TL","color":"#D4FF00"},{"arabic":"تفسيريّة","atr":"H.TF","color":"#D4FF00"},{"arabic":"تنبيهيّه","atr":"H.TN","color":"#D4FF00"},{"arabic":"جارّة","atr":"H.JR","color":"#563128"},{"arabic":"جواب شرط","atr":"H.JSH","color":"#2AAAFF"},{"arabic":"حاليّة","atr":"H.HL","color":"#A8017B"},{"arabic":"حرف استقبال","atr":"H.EST","color":"#A8017B"},{"arabic":"حرف جواب","atr":"H.JV","color":"#563128"},{"arabic":"زائدة","atr":"H.ZA","color":"#A8017B"},{"arabic":"زائدة اللصوقيّة","atr":"H.ZAL","color":"#1301B8"},{"arabic":"زائده","atr":"H.ZA","color":"#563128"},{"arabic":"شبيه به ليس","atr":"H.LS","color":"#1301B8"},{"arabic":"شرطيّة","atr":"H.SHR","color":"#2AAAFF"},{"arabic":"شرطية التّأکيدية الـتّفصيلية","atr":"H.SH.T","color":"#1301B8"},{"arabic":"عاطفة","atr":"H.ET","color":"#AD2323"},{"arabic":"فجائيّة","atr":"H.FJ","color":"#FF5500"},{"arabic":"لام امر","atr":"H.AMR","color":"#AD2323"},{"arabic":"مخففه از ثقيلة","atr":"H.MS","color":"#7A57BB"},{"arabic":"مشبهة بالفعل","atr":"H.MF","color":"#FF5500"},{"arabic":"مصدريّةغير زمانيه","atr":"H.MQZ","color":"#AD2323"},{"arabic":"مصدرية","atr":"H.M","color":"#AD2323"},{"arabic":"مصدريه زمانيه","atr":"H.MZ","color":"#FF5500"},{"arabic":"موطئة للقسم","atr":"H.MQS","color":"#AD2323"},{"arabic":"نا فية للجنس","atr":"H.NJ","color":"#7A57BB"},{"arabic":"ناصبة","atr":"H.NS","color":"#FF5500"},{"arabic":"نافية","atr":"H.NF","color":"#548DD4"},{"arabic":"ناهيّة","atr":"H.NH","color":"#548DD4"},{"arabic":"ندا","atr":"H.ND","color":"#FF5500"},{"arabic":"نفي و استقبال","atr":"H.NFS","color":"#548DD4"},{"arabic":"وصليّة","atr":"H.VO","color":"#FF5500"},{"arabic":"مبهم","atr":"M","color":"#548DD4"},{"arabic":"ضمير متصل غائب منصوبي مجروري","atr":"E.ZTGSJ","color":"#AD2552"},{"arabic":"ضمير متصل متكلم","atr":"E.ZTK","color":"#445706"},{"arabic":"ضمير متصل مخاطب منصوبي مجروري","atr":"E.ZTKHSJ","color":"#AD9765"},{"arabic":"ضمير متصل مرفوعي","atr":"E.ZTGF","color":"#7A57BB"},{"arabic":"الف زينت","atr":"H.NON","color":"#AF2200"},{"arabic":"نون عوض رفع","atr":"H.NON1","color":"#130645"},{"arabic":"تاء تانیث","atr":"H.NON2","color":"#FF5500"},{"arabic":"مقدر","atr":"Z.M","color":"#C5C5C5"}],"TotalCount":77,"Id":"0","IsSuccess":true,"Message":"OK","StatusCode":200,"ValidationMessages":null,"Exception":null,"ResponseTime":"2020-12-02T12:14:58.4929561Z"},"relationName":{"Data":[{"color":"#83ADE0","name":"فاعل","Id":1},{"color":"#445706","name":"مستثنا","Id":2},{"color":"#70869C","name":"خبر","Id":3},{"color":"#70869C","name":"مفعول به","Id":4},{"color":"#D73535","name":"مجرور","Id":5},{"color":"#6F9FDB","name":"مضاف الیه ","Id":6},{"color":"#495706","name":"حال","Id":7},{"color":"#9A3CD9","name":"نعت","Id":8},{"color":"#6F9FDB","name":"بدل","Id":9},{"color":"#4C5706","name":"تمییز","Id":10},{"color":"#7FAAFF","name":"معطوف","Id":11},{"color":"#D8019C","name":"توکید","Id":12},{"color":"#EF7D21","name":"متعلق","Id":13},{"color":"#505706","name":"اسم","Id":14},{"color":"#97881C","name":"صله","Id":15},{"color":"#525706","name":"مفعول معه","Id":16},{"color":"#83ADE0","name":"نائب فاعل","Id":17},{"color":"#AD2323","name":"عطف بیان","Id":18},{"color":"#D8019C","name":"مفعول مطلق","Id":19},{"color":"#D73535","name":"ظرف","Id":20},{"color":"#70869C","name":"شرط","Id":21},{"color":"#7FAAFF","name":"جواب شرط","Id":22},{"color":"#70869C","name":"مفعول له","Id":23},{"color":"#4C5706","name":"منادا","Id":24},{"color":"#83ADE0","name":"جواب امر","Id":25},{"color":"#D8019C","name":"منصوب به نزع خافض","Id":26},{"color":"#4C5706","name":"جواب ندا","Id":27},{"color":"#83ADE0","name":"جواب قسم","Id":28},{"color":"#4C5706","name":"تعریف","Id":29},{"color":"#D8019C","name":"ضمیر فصل","Id":30},{"color":"#D73535","name":"استثنا","Id":31},{"color":"#EF7D21","name":"زائد","Id":32},{"color":"#7FAAFF","name":"مشتغل عنه","Id":33},{"color":"#4C5706","name":"معطوف بر محل","Id":34},{"color":"#97881C","name":"تأکید","Id":35},{"color":"#7FAAFF","name":"تحقیق","Id":36},{"color":"#7FAAFF","name":"استقبال","Id":37},{"color":"#7FAAFF","name":"استفهام","Id":38},{"color":"#70869C","name":"نفی","Id":39},{"color":"#97881C","name":"نهی","Id":40},{"color":"#83ADE0","name":"حصر","Id":41},{"color":"#83ADE0","name":"جر زائد","Id":42},{"color":"#D8019C","name":"ابتدا","Id":43},{"color":"#445706","name":"تنبیه","Id":44},{"color":"#97881C","name":"حرف جواب","Id":45},{"color":"#445706","name":"سکت","Id":46},{"color":"#70869C","name":"طلب","Id":47},{"color":"#D8019C","name":"استیناف","Id":48},{"color":"#D8019C","name":"تحضیض","Id":49},{"color":"#83ADE0","name":"تفسیر","Id":50},{"color":"#70869C","name":"تفصیل","Id":51},{"color":"#D8019C","name":"جواب","Id":52},{"color":"#445706","name":"اعتراض","Id":53},{"color":"#D8019C","name":"موطئه","Id":54},{"color":"#7FAAFF","name":"عطف","Id":55},{"color":"#70869C","name":"مفاجاة","Id":56},{"color":"#7FAAFF","name":"مخففه","Id":57},{"color":"#D73535","name":"معیه","Id":58},{"color":"#445706","name":"مصدریه","Id":59},{"color":"#D8019C","name":"اشباع","Id":60},{"color":"#70869C","name":"حالیه","Id":61},{"color":"#D8019C","name":"وقایه","Id":62},{"color":"#FF2200","name":"الف زینت","Id":63},{"color":"#130645","name":"نون عوض رفع","Id":64},{"color":"#FF5500","name":"تاء تانیث","Id":65}],"TotalCount":65,"Id":"0","IsSuccess":true,"Message":"OK","StatusCode":200,"ValidationMessages":null,"Exception":null,"ResponseTime":"2020-12-02T12:14:58.4929561Z"},"ayeh":{"node":{"Data":[{"atrId":65,"delete":0,"id":112770,"idWord":82849,"nextId":112771,"prevId":null,"Word":"يَا","xml":"<word Seq=\"1\" Entry=\"يَا\" Affix=\"هسته\" Pos=\"حرف\" Case=\"مبنی بر سکون\" Kol=\"ندا\" Slice=\"يَا\" />","isNewWord":0},{"atrId":18,"delete":0,"id":112771,"idWord":82850,"nextId":112772,"prevId":112770,"Word":"أَیُّ","xml":"<word Seq=\"1\" Slice=\"أَیُّ\" Entry=\"أَيُّ\" Affix=\"هسته\" Pos=\"اسم\" Case=\"مبنی بر ضم\" Categ=\"تهی\" Def=\"نکره\" Derv=\"\" DervT=\"أی وصلیه\" Gend=\"مذکر\" Num=\"تهی\" Root=\"تهی\" RootT=\"تهی\" Temp=\"تهی\" Varied=\"تهی\" Decl=\"\" />","isNewWord":0},{"atrId":40,"delete":0,"id":112772,"idWord":82850,"nextId":112773,"prevId":112771,"Word":"هَا","xml":"<word Seq=\"2\" Slice=\"هَا\" Entry=\"هَا\" Affix=\"پسوند\" Pos=\"حرف\" Case=\"مبنی بر سکون\" Kol=\"تنبیهیه\" />","isNewWord":0},{"atrId":26,"delete":0,"id":112773,"idWord":82851,"nextId":112774,"prevId":112772,"Word":"الَّذِينَ ","xml":"<word Seq=\"1\" Entry=\"الَّذِینَ\" Affix=\"هسته\" Pos=\"اسم\" Case=\"مبنی بر فتح\" Categ=\"تهی\" Def=\"معرفه\" Derv=\"\" DervT=\"اسم موصول\" Gend=\"مذکر\" Num=\"جمع\" Root=\"تهی\" RootT=\"تهی\" Temp=\"تهی\" Varied=\"تهی\" Decl=\"\" Slice=\"الَّذِينَ \" />","isNewWord":0},{"atrId":1,"delete":0,"id":112774,"idWord":82852,"nextId":152551,"prevId":112773,"Word":"آمَن","xml":"<word Seq=\"1\" Entry=\"آمَن\" Affix=\"هسته\" Pos=\"فعل\" Case=\"مبنی بر ضم\" Categ=\"افعال\" Gend=\"مذکر\" Num=\"جمع\" Root=\"ءمن\" RootT=\"مهموز الفاء\" Temp=\"أَفْعَلُوا\" Time=\"ماضی\" TOV=\"3\" Trans=\"لازم\" Voic=\"معلوم\" Slice=\"آمَن\" />","isNewWord":0},{"atrId":64,"delete":0,"id":112775,"idWord":82853,"nextId":112776,"prevId":152552,"Word":"لَا","xml":"<word Seq=\"1\" Slice=\"لَا\" Entry=\"لَا\" Affix=\"هسته\" Pos=\"حرف\" Case=\"مبنی بر سکون\" Kol=\"ناهیه\" />","isNewWord":0},{"atrId":3,"delete":0,"id":112776,"idWord":82854,"nextId":152553,"prevId":112775,"Word":"تَتَّخِذ","xml":"<word Seq=\"1\" Slice=\"تَتَّخِذ\" Entry=\"تَتَّخِذ\" Affix=\"هسته\" Pos=\"فعل\" Case=\"مجزوم\" Categ=\"افتعال\" Gend=\"مذکر\" Num=\"جمع\" Root=\"أخذ\" RootT=\"مهموز الفاء\" Temp=\"تَفْتَعِلُوا\" Time=\"مضارع ساده\" TOV=\"9\" Trans=\"متعدی\" Voic=\"معلوم\" />","isNewWord":0},{"atrId":24,"delete":0,"id":112777,"idWord":82855,"nextId":112778,"prevId":152554,"Word":"عَدُوِّ","xml":"<word Seq=\"1\" Slice=\"عَدُوِّ\" Entry=\"عَدُوِّ\" Affix=\"هسته\" Pos=\"اسم\" Case=\"اعراب تقدیری\" Categ=\"فَعَلَ یَفْعُلُ\" Def=\"معرفه\" DervT=\"صفت مشبهه\" Gend=\"مذکر\" Num=\"مفرد\" Root=\"عدو\" RootT=\"ناقص واوی\" Temp=\"فَعُلِّ\" Varied=\"منصرف\" />","isNewWord":0},{"atrId":70,"delete":0,"id":112778,"idWord":82855,"nextId":112779,"prevId":112777,"Word":"ی","xml":"<word Seq=\"2\" Slice=\"ی\" Entry=\"ی\" Affix=\"پسوند\" Pos=\"اسم\" Case=\"مبنی بر سکون\" Categ=\"تهی\" Def=\"معرفه\" DervT=\"ضمیر متصل منصوبی مجروری\" Gend=\"تهی\" Num=\"مفرد\" Root=\"تهی\" RootT=\"تهی\" Temp=\"تهی\" Varied=\"تهی\" />","isNewWord":0},{"atrId":52,"delete":0,"id":112779,"idWord":82856,"nextId":112780,"prevId":112778,"Word":"وَ","xml":"<word Seq=\"1\" Slice=\"وَ\" Entry=\"وَ\" Affix=\"هسته\" Pos=\"حرف\" Lemma=\"وَ\" Case=\"مبنی بر فتح\" Kol=\"عاطفه\" Desc=\"\" />","isNewWord":0},{"atrId":24,"delete":0,"id":112780,"idWord":82857,"nextId":112781,"prevId":112779,"Word":"عَدُوَّ","xml":"<word Seq=\"1\" Slice=\"عَدُوَّ\" Entry=\"عَدُوَّ\" Affix=\"هسته\" Pos=\"اسم\" Case=\"منصوب\" Categ=\"فَعَلَ یَفْعُلُ\" Def=\"اضافه\" DervT=\"صفت مشبهه\" Gend=\"مذکر\" Num=\"مفرد\" Root=\"عدو\" RootT=\"ناقص واوی\" Temp=\"فَعُلَّ\" Varied=\"منصرف\" />","isNewWord":0},{"atrId":71,"delete":0,"id":112781,"idWord":82857,"nextId":112782,"prevId":112780,"Word":"کُمْ","xml":"<word Seq=\"2\" Slice=\"کُمْ\" Entry=\"کُمْ\" Affix=\"پسوند\" Pos=\"اسم\" Case=\"مبنی بر سکون\" Categ=\"تهی\" Def=\"معرفه\" DervT=\"ضمیر متصل منصوبی مجروری\" Gend=\"مذکر\" Num=\"جمع\" Root=\"تهی\" RootT=\"تهی\" Temp=\"تهی\" Varied=\"تهی\" />","isNewWord":0},{"atrId":19,"delete":0,"id":112782,"idWord":82858,"nextId":112783,"prevId":112781,"Word":"أَوْلِيَاءَ","xml":"<word Seq=\"1\" Slice=\"أَوْلِيَاءَ\" Entry=\"أَوْلِيَاءَ\" Affix=\"هسته\" Pos=\"اسم\" Case=\"منصوب\" Categ=\"فَعِلَ یَفْعِلُ\" Def=\"نکره\" Derv=\"\" DervT=\"صفت مشبهه\" Gend=\"مذکر\" Num=\"جمع مکسر\" Root=\"ولی\" RootT=\"لفیف مفروق\" Temp=\"أَفْعِلَاءَ\" Varied=\"منصرف\" Decl=\"\" />","isNewWord":0},{"atrId":1,"delete":0,"id":112783,"idWord":82859,"nextId":152555,"prevId":112782,"Word":"تُلْق","xml":"<word Seq=\"1\" Slice=\"تُلْق\" Entry=\"تُلْق\" Affix=\"هسته\" Pos=\"فعل\" Case=\"مرفوع\" Categ=\"افعال\" Gend=\"مذکر\" Num=\"جمع\" Root=\"لقی\" RootT=\"ناقص یائی\" Temp=\"تُفْعِلُونَ\" Time=\"مضارع ساده\" TOV=\"9\" Trans=\"متعدی\" Voic=\"معلوم\" />","isNewWord":0},{"atrId":41,"delete":0,"id":112784,"idWord":82860,"nextId":112785,"prevId":152556,"Word":"إِلَیْ","xml":"<word Seq=\"1\" Entry=\"إِلَی\" Affix=\"پیشوند\" Pos=\"حرف\" Case=\"مبنی بر سکون\" Kol=\"جاره\" Slice=\"إِلَیْ\" />","isNewWord":0},{"atrId":21,"delete":0,"id":112785,"idWord":82860,"nextId":112786,"prevId":112784,"Word":"هِمْ","xml":"<word Seq=\"2\" Entry=\"هُمْ\" Affix=\"هسته\" Pos=\"اسم\" Case=\"مبنی بر سکون\" Categ=\"تهی\" Def=\"معرفه\" Derv=\"\" DervT=\"ضمیر متصل منصوبی مجروری\" Gend=\"مذکر\" Num=\"جمع\" Root=\"تهی\" RootT=\"تهی\" Temp=\"تهی\" Varied=\"تهی\" Decl=\"\" Slice=\"هِمْ\" />","isNewWord":0},{"atrId":41,"delete":0,"id":112786,"idWord":82861,"nextId":112787,"prevId":112785,"Word":"بِ","xml":"<word Seq=\"1\" Slice=\"بِ\" Entry=\"بِ\" Affix=\"پیشوند\" Pos=\"حرف\" Case=\"مبنی بر کسر\" Kol=\"جاره\" />","isNewWord":0},{"atrId":37,"delete":0,"id":112787,"idWord":82861,"nextId":112788,"prevId":112786,"Word":"الْ","xml":"<word Seq=\"2\" Slice=\"الْ\" Entry=\"الْ\" Affix=\"پیشوند\" Pos=\"حرف\" Case=\"مبنی بر سکون\" Kol=\"تعریف\" />","isNewWord":0},{"atrId":25,"delete":0,"id":112788,"idWord":82861,"nextId":112789,"prevId":112787,"Word":"مَوَدَّةِ","xml":"<word Seq=\"3\" Slice=\"مَوَدَّةِ\" Entry=\"مَوَدَّةِ\" Affix=\"هسته\" Pos=\"اسم\" Case=\"مجرور\" Categ=\"فَعِلَ یَفْعَلُ\" Def=\"معرفه\" DervT=\"مصدر میمی\" Gend=\"مؤنث\" Num=\"مفرد\" Root=\"ودد\" RootT=\"مثال واوی مضاعف\" Temp=\"مَفَعْلَةِ\" Varied=\"منصرف\" />","isNewWord":0},{"atrId":43,"delete":0,"id":112789,"idWord":82862,"nextId":112790,"prevId":112788,"Word":"وَ","xml":"<word Seq=\"1\" Slice=\"وَ\" Entry=\"وَ\" Affix=\"هسته\" Pos=\"حرف\" Lemma=\"وَ\" Case=\"مبنی بر فتح\" Kol=\"حالیه\" Desc=\"\" />","isNewWord":0},{"atrId":36,"delete":0,"id":112790,"idWord":82863,"nextId":112791,"prevId":112789,"Word":"قَدْ","xml":"<word Seq=\"1\" Entry=\"قَدْ\" Affix=\"هسته\" Pos=\"حرف\" Case=\"مبنی بر سکون\" Kol=\"تحقیقیه\" Slice=\"قَدْ\" />","isNewWord":0},{"atrId":1,"delete":0,"id":112791,"idWord":82864,"nextId":152557,"prevId":112790,"Word":"کَفَر","xml":"<word Seq=\"1\" Entry=\"كَفَر\" Affix=\"هسته\" Pos=\"فعل\" Case=\"مبنی بر ضم\" Categ=\"فَعَلَ یَفْعُلُ\" Gend=\"مذکر\" Num=\"جمع\" Root=\"کفر\" RootT=\"سالم\" Temp=\"فَعَلُوا\" Time=\"ماضی\" TOV=\"3\" Trans=\"لازم\" Voic=\"معلوم\" Slice=\"کَفَر\" />","isNewWord":0},{"atrId":41,"delete":0,"id":112792,"idWord":82865,"nextId":112793,"prevId":152558,"Word":"بِ","xml":"<word Seq=\"1\" Slice=\"بِ\" Entry=\"بِ\" Affix=\"هسته\" Pos=\"حرف\" Case=\"مبنی بر کسر\" Kol=\"جاره\" />","isNewWord":0},{"atrId":26,"delete":0,"id":112793,"idWord":82865,"nextId":112794,"prevId":112792,"Word":"مَا","xml":"<word Seq=\"2\" Slice=\"مَا\" Entry=\"مَا\" Affix=\"هسته\" Pos=\"اسم\" Case=\"مبنی بر سکون\" Categ=\"تهی\" Def=\"معرفه\" DervT=\"اسم موصول\" Gend=\"تهی\" Num=\"مشترک\" Root=\"تهی\" RootT=\"تهی\" Temp=\"تهی\" Varied=\"تهی\" />","isNewWord":0},{"atrId":3,"delete":0,"id":112794,"idWord":82866,"nextId":155685,"prevId":112793,"Word":"جَاءَ","xml":"<word Seq=\"1\" Slice=\"جَاءَ\" Entry=\"جَاءَ\" Affix=\"هسته\" Pos=\"فعل\" Case=\"مبنی بر فتح\" Categ=\"فَعَلَ یَفْعِلُ\" Gend=\"مذکر\" Num=\"مفرد\" Root=\"جیء\" RootT=\"اجوف یائی مهموز اللام\" Temp=\"فَعَلَ\" Time=\"ماضی\" TOV=\"1\" Trans=\"متعدی\" Voic=\"معلوم\" />","isNewWord":0},{"atrId":71,"delete":0,"id":112795,"idWord":82866,"nextId":135673,"prevId":155685,"Word":"کُمْ","xml":"<word Seq=\"2\" Slice=\"کُمْ\" Entry=\"كُمْ\" Affix=\"پسوند\" Pos=\"اسم\" Case=\"مبنی بر سکون\" Categ=\"تهی\" Def=\"معرفه\" Derv=\"\" DervT=\"ضمیر متصل منصوبی مجروری\" Gend=\"مذکر\" Num=\"جمع\" Root=\"تهی\" RootT=\"تهی\" Temp=\"تهی\" Varied=\"تهی\" Decl=\"\" />","isNewWord":0},{"atrId":41,"delete":0,"id":112796,"idWord":82867,"nextId":112797,"prevId":135673,"Word":"مِنَ","xml":"<word Seq=\"1\" Entry=\"مِنْ\" Affix=\"هسته\" Pos=\"حرف\" Case=\"مبنی بر سکون\" Kol=\"جاره\" Slice=\"مِنَ\" />","isNewWord":0},{"atrId":37,"delete":0,"id":112797,"idWord":82868,"nextId":112798,"prevId":112796,"Word":"الْ","xml":"<word Seq=\"1\" Entry=\"الْ\" Affix=\"پیشوند\" Pos=\"حرف\" Case=\"مبنی بر سکون\" Kol=\"تعریف\" Slice=\"الْ\" />","isNewWord":0},{"atrId":24,"delete":0,"id":112798,"idWord":82868,"nextId":112799,"prevId":112797,"Word":"حَقِّ","xml":"<word Seq=\"2\" Entry=\"حَقِّ\" Affix=\"هسته\" Pos=\"اسم\" Case=\"مجرور\" Categ=\"فَعَلَ یَفْعِلُ\" Def=\"معرفه\" Derv=\"\" DervT=\"مصدر\" Gend=\"مذکر\" Num=\"مفرد\" Root=\"حقق\" RootT=\"مضاعف\" Temp=\"فَعْلِ\" Varied=\"منصرف\" Decl=\"\" Slice=\"حَقِّ\" />","isNewWord":0},{"atrId":3,"delete":0,"id":112799,"idWord":82869,"nextId":152559,"prevId":112798,"Word":"یُخْرِج","xml":"<word Seq=\"1\" Slice=\"یُخْرِج\" Entry=\"یُخْرِج\" Affix=\"هسته\" Pos=\"فعل\" Case=\"مرفوع\" Categ=\"افعال\" Gend=\"مذکر\" Num=\"جمع\" Root=\"خرج\" RootT=\"سالم\" Temp=\"یُفْعِلُونَ\" Time=\"مضارع ساده\" TOV=\"3\" Trans=\"متعدی\" Voic=\"معلوم\" />","isNewWord":0},{"atrId":37,"delete":0,"id":112800,"idWord":82870,"nextId":112801,"prevId":152560,"Word":"ال","xml":"<word Seq=\"1\" Slice=\"ال\" Entry=\"الْ\" Affix=\"پیشوند\" Pos=\"حرف\" Case=\"مبنی بر سکون\" Kol=\"تعریف\" />","isNewWord":0},{"atrId":19,"delete":0,"id":112801,"idWord":82870,"nextId":112802,"prevId":112800,"Word":"رَّسُولَ","xml":"<word Seq=\"2\" Slice=\"رَّسُولَ\" Entry=\"رَسُولَ\" Affix=\"هسته\" Pos=\"اسم\" Case=\"منصوب\" Categ=\"افعال\" Def=\"معرفه\" Derv=\"\" DervT=\"صفت مشبهه\" Gend=\"مذکر\" Num=\"مفرد\" Root=\"رسل\" RootT=\"سالم\" Temp=\"فَعُولَ\" Varied=\"منصرف\" Decl=\"\" />","isNewWord":0},{"atrId":52,"delete":0,"id":112802,"idWord":82871,"nextId":112803,"prevId":112801,"Word":"وَ","xml":"<word Seq=\"1\" Slice=\"وَ\" Entry=\"وَ\" Affix=\"هسته\" Pos=\"حرف\" Lemma=\"وَ\" Case=\"مبنی بر فتح\" Kol=\"عاطفه\" Desc=\"\" />","isNewWord":0},{"atrId":22,"delete":0,"id":112803,"idWord":82872,"nextId":112804,"prevId":112802,"Word":"إِيَّاكُمْ","xml":"<word Seq=\"1\" Slice=\"إِيَّاكُمْ\" Entry=\"إِيَّاكُمْ\" Affix=\"هسته\" Pos=\"اسم\" Case=\"مبنی بر سکون\" Categ=\"تهی\" Def=\"معرفه\" Derv=\"\" DervT=\"ضمیر منفصل منصوبی\" Gend=\"مذکر\" Num=\"جمع\" Root=\"تهی\" RootT=\"تهی\" Temp=\"تهی\" Varied=\"تهی\" Decl=\"\" />","isNewWord":0},{"atrId":62,"delete":0,"id":112804,"idWord":82873,"nextId":112805,"prevId":112803,"Word":"أَنْ","xml":"<word Seq=\"1\" Slice=\"أَنْ\" Entry=\"أَنْ\" Affix=\"هسته\" Pos=\"حرف\" Case=\"مبنی بر سکون\" Kol=\"مصدریه\" />","isNewWord":0},{"atrId":1,"delete":0,"id":112805,"idWord":82874,"nextId":152561,"prevId":112804,"Word":"تُؤْمِن","xml":"<word Seq=\"1\" Slice=\"تُؤْمِن\" Entry=\"تُؤْمِن\" Affix=\"هسته\" Pos=\"فعل\" Case=\"منصوب\" Categ=\"افعال\" Gend=\"مذکر\" Num=\"جمع\" Root=\"ءمن\" RootT=\"مهموز الفاء\" Temp=\"تُفْعِلُوا\" Time=\"مضارع ساده\" TOV=\"9\" Trans=\"لازم\" Voic=\"معلوم\" />","isNewWord":0},{"atrId":41,"delete":0,"id":112806,"idWord":82875,"nextId":112807,"prevId":152562,"Word":"بِ","xml":"<word Seq=\"1\" Entry=\"بِ\" Affix=\"پیشوند\" Pos=\"حرف\" Case=\"مبنی بر کسر\" Kol=\"جاره\" Slice=\"بِ\" />","isNewWord":0},{"atrId":4,"delete":0,"id":112807,"idWord":82875,"nextId":112808,"prevId":112806,"Word":"اللَّهِ","xml":"<word Seq=\"2\" Entry=\"اَللَهِ\" Affix=\"هسته\" Pos=\"اسم\" Case=\"مجرور\" Categ=\"ثلاثی مجرد\" Def=\"معرفه\" DervT=\"جامد غیر مصدری\" Alam=\"آری\" Gend=\"مذکر\" Num=\"مفرد\" Root=\"ءله\" RootT=\"مهموز الفاء\" Temp=\"تهی\" Varied=\"منصرف\" Slice=\"اللَّهِ\" />","isNewWord":0},{"atrId":24,"delete":0,"id":112808,"idWord":82876,"nextId":112809,"prevId":112807,"Word":"رَبِّ","xml":"<word Seq=\"1\" Entry=\"رَبِّ\" Affix=\"هسته\" Pos=\"اسم\" Case=\"مجرور\" Categ=\"فَعَلَ یَفْعُلُ\" Def=\"اضافه\" Derv=\"\" DervT=\"جامد غیر مصدری\" Gend=\"مذکر\" Num=\"مفرد\" Root=\"ربب\" RootT=\"مضاعف\" Temp=\"فَعْلِ\" Varied=\"منصرف\" Decl=\"\" Slice=\"رَبِّ\" />","isNewWord":0},{"atrId":71,"delete":0,"id":112809,"idWord":82876,"nextId":112810,"prevId":112808,"Word":"کُمْ","xml":"<word Seq=\"2\" Entry=\"کُمْ\" Affix=\"پسوند\" Pos=\"اسم\" Case=\"مبنی بر سکون\" Categ=\"تهی\" Def=\"معرفه\" Derv=\"\" DervT=\"ضمیر متصل منصوبی مجروری\" Gend=\"مذکر\" Num=\"جمع\" Root=\"تهی\" RootT=\"تهی\" Temp=\"تهی\" Varied=\"تهی\" Decl=\"\" Slice=\"کُمْ\" />","isNewWord":0},{"atrId":50,"delete":0,"id":112810,"idWord":82877,"nextId":112811,"prevId":112809,"Word":"إِنْ","xml":"<word Seq=\"1\" Slice=\"إِنْ\" Entry=\"إِنْ\" Affix=\"هسته\" Pos=\"حرف\" Case=\"مبنی بر سکون\" Kol=\"شرطیه\" />","isNewWord":0},{"atrId":1,"delete":0,"id":112811,"idWord":82878,"nextId":152563,"prevId":112810,"Word":"کُن","xml":"<word Seq=\"1\" Entry=\"کُن\" Affix=\"هسته\" Pos=\"فعل\" Case=\"مبنی بر سکون\" Categ=\"فَعَلَ یَفْعُلُ\" Gend=\"مذکر\" Num=\"جمع\" Root=\"کون\" RootT=\"اجوف واوی\" Temp=\"فَعَلْتُمْ\" Time=\"ماضی\" TOV=\"9\" Trans=\"متعدی\" Voic=\"معلوم\" Slice=\"کُن\" />","isNewWord":0},{"atrId":1,"delete":0,"id":112812,"idWord":82879,"nextId":152564,"prevId":152563,"Word":"خَرَج","xml":"<word Seq=\"1\" Slice=\"خَرَج\" Entry=\"خَرَج\" Affix=\"هسته\" Pos=\"فعل\" Case=\"مبنی بر سکون\" Categ=\"فَعَلَ یَفْعُلُ\" Gend=\"مذکر\" Num=\"جمع\" Root=\"خرج\" RootT=\"سالم\" Temp=\"فَعَلْتُمْ\" Time=\"ماضی\" TOV=\"9\" Trans=\"لازم\" Voic=\"معلوم\" />","isNewWord":0},{"atrId":24,"delete":0,"id":112813,"idWord":82880,"nextId":112814,"prevId":152564,"Word":"جِهَادًا","xml":"<word Seq=\"1\" Slice=\"جِهَادًا\" Entry=\"جِهَادًا\" Affix=\"هسته\" Pos=\"اسم\" Case=\"منصوب\" Categ=\"مفاعله\" Def=\"نکره\" Derv=\"\" DervT=\"مصدر\" Gend=\"مذکر\" Num=\"مفرد\" Root=\"جهد\" RootT=\"سالم\" Temp=\"فِعَالًا\" Varied=\"منصرف\" Decl=\"\" />","isNewWord":0},{"atrId":41,"delete":0,"id":112814,"idWord":82881,"nextId":112815,"prevId":112813,"Word":"فِي","xml":"<word Seq=\"1\" Entry=\"فِی\" Affix=\"هسته\" Pos=\"حرف\" Case=\"مبنی بر سکون\" Kol=\"جاره\" Slice=\"فِي\" />","isNewWord":0},{"atrId":4,"delete":0,"id":112815,"idWord":82882,"nextId":112816,"prevId":112814,"Word":"سَبِیلِ","xml":"<word Seq=\"1\" Slice=\"سَبِیلِ\" Entry=\"سَبِیلِ\" Affix=\"هسته\" Pos=\"اسم\" Case=\"اعراب تقدیری\" Categ=\"ثلاثی مجرد\" Def=\"اضافه\" DervT=\"جامد غیر مصدری\" Gend=\"مذکر\" Num=\"مفرد\" Root=\"سبل\" RootT=\"سالم\" Temp=\"فَعِیلِ\" Varied=\"منصرف\" />","isNewWord":0},{"atrId":70,"delete":0,"id":112816,"idWord":82882,"nextId":112817,"prevId":112815,"Word":"ی","xml":"<word Seq=\"2\" Slice=\"ی\" Entry=\"ی\" Affix=\"پسوند\" Pos=\"اسم\" Case=\"مبنی بر سکون\" Categ=\"تهی\" Def=\"معرفه\" DervT=\"ضمیر متصل منصوبی مجروری\" Gend=\"تهی\" Num=\"مفرد\" Root=\"تهی\" RootT=\"تهی\" Temp=\"تهی\" Varied=\"تهی\" />","isNewWord":0},{"atrId":52,"delete":0,"id":112817,"idWord":82883,"nextId":112818,"prevId":112816,"Word":"وَ","xml":"<word Seq=\"1\" Slice=\"وَ\" Entry=\"وَ\" Affix=\"هسته\" Pos=\"حرف\" Lemma=\"وَ\" Case=\"مبنی بر فتح\" Kol=\"عاطفه\" Desc=\"\" />","isNewWord":0},{"atrId":24,"delete":0,"id":112818,"idWord":82884,"nextId":112819,"prevId":112817,"Word":"اِبْتِغَاءَ","xml":"<word Seq=\"1\" Slice=\"اِبْتِغَاءَ\" Entry=\"اِبْتِغَاءَ\" Affix=\"هسته\" Pos=\"اسم\" Case=\"منصوب\" Categ=\"افتعال\" Def=\"اضافه\" Derv=\"\" DervT=\"مصدر\" Gend=\"مذکر\" Num=\"مفرد\" Root=\"بغی\" RootT=\"ناقص یائی\" Temp=\"اِفْتِعَالَ\" Varied=\"منصرف\" Decl=\"\" />","isNewWord":0},{"atrId":25,"delete":0,"id":112819,"idWord":82885,"nextId":112820,"prevId":112818,"Word":"مَرْضَاتِ","xml":"<word Seq=\"1\" Slice=\"مَرْضَاتِ\" Entry=\"مَرْضَاتِ\" Affix=\"هسته\" Pos=\"اسم\" Case=\"اعراب تقدیری\" Categ=\"فَعِلَ یَفْعَلُ\" Def=\"اضافه\" DervT=\"مصدر میمی\" Gend=\"مؤنث\" Num=\"مفرد\" Root=\"رضو\" RootT=\"ناقص واوی\" Temp=\"مَفْعَلَةِ\" Varied=\"منصرف\" />","isNewWord":0},{"atrId":70,"delete":0,"id":112820,"idWord":82885,"nextId":112821,"prevId":112819,"Word":"ی","xml":"<word Seq=\"2\" Slice=\"ی\" Entry=\"ی\" Affix=\"پسوند\" Pos=\"اسم\" Case=\"مبنی بر سکون\" Categ=\"تهی\" Def=\"معرفه\" DervT=\"ضمیر متصل منصوبی مجروری\" Gend=\"تهی\" Num=\"مفرد\" Root=\"تهی\" RootT=\"تهی\" Temp=\"تهی\" Varied=\"تهی\" />","isNewWord":0},{"atrId":3,"delete":0,"id":112821,"idWord":82886,"nextId":152565,"prevId":112820,"Word":"تُسِرّ","xml":"<word Seq=\"1\" Slice=\"تُسِرّ\" Entry=\"تُسِرُّ\" Affix=\"هسته\" Pos=\"فعل\" Case=\"مرفوع\" Categ=\"افعال\" Gend=\"مذکر\" Num=\"جمع\" Root=\"سرر\" RootT=\"مضاعف\" Temp=\"تُفْعِلُونَ\" Time=\"مضارع ساده\" TOV=\"9\" Trans=\"لازم و متعدی\" Voic=\"معلوم\" />","isNewWord":0},{"atrId":41,"delete":0,"id":112822,"idWord":82887,"nextId":112823,"prevId":152566,"Word":"إِلَیْ","xml":"<word Seq=\"1\" Entry=\"إِلَی\" Affix=\"پیشوند\" Pos=\"حرف\" Case=\"مبنی بر سکون\" Kol=\"جاره\" Slice=\"إِلَیْ\" />","isNewWord":0},{"atrId":21,"delete":0,"id":112823,"idWord":82887,"nextId":112824,"prevId":112822,"Word":"هِمْ","xml":"<word Seq=\"2\" Entry=\"هُمْ\" Affix=\"هسته\" Pos=\"اسم\" Case=\"مبنی بر سکون\" Categ=\"تهی\" Def=\"معرفه\" Derv=\"\" DervT=\"ضمیر متصل منصوبی مجروری\" Gend=\"مذکر\" Num=\"جمع\" Root=\"تهی\" RootT=\"تهی\" Temp=\"تهی\" Varied=\"تهی\" Decl=\"\" Slice=\"هِمْ\" />","isNewWord":0},{"atrId":41,"delete":0,"id":112824,"idWord":82888,"nextId":112825,"prevId":112823,"Word":"بِ","xml":"<word Seq=\"1\" Slice=\"بِ\" Entry=\"بِ\" Affix=\"پیشوند\" Pos=\"حرف\" Case=\"مبنی بر کسر\" Kol=\"جاره\" />","isNewWord":0},{"atrId":37,"delete":0,"id":112825,"idWord":82888,"nextId":112826,"prevId":112824,"Word":"الْ","xml":"<word Seq=\"2\" Slice=\"الْ\" Entry=\"الْ\" Affix=\"پیشوند\" Pos=\"حرف\" Case=\"مبنی بر سکون\" Kol=\"تعریف\" />","isNewWord":0},{"atrId":25,"delete":0,"id":112826,"idWord":82888,"nextId":112827,"prevId":112825,"Word":"مَوَدَّةِ","xml":"<word Seq=\"3\" Slice=\"مَوَدَّةِ\" Entry=\"مَوَدَّةِ\" Affix=\"هسته\" Pos=\"اسم\" Case=\"مجرور\" Categ=\"فَعِلَ یَفْعَلُ\" Def=\"معرفه\" DervT=\"مصدر میمی\" Gend=\"مؤنث\" Num=\"مفرد\" Root=\"ودد\" RootT=\"مثال واوی مضاعف\" Temp=\"مَفَعْلَةِ\" Varied=\"منصرف\" />","isNewWord":0},{"atrId":43,"delete":0,"id":112827,"idWord":82889,"nextId":112828,"prevId":112826,"Word":"وَ","xml":"<word Seq=\"1\" Slice=\"وَ\" Entry=\"وَ\" Affix=\"هسته\" Pos=\"حرف\" Lemma=\"وَ\" Case=\"مبنی بر فتح\" Kol=\"حالیه\" Desc=\"\" />","isNewWord":0},{"atrId":22,"delete":0,"id":112828,"idWord":82890,"nextId":112829,"prevId":112827,"Word":"أَنَا","xml":"<word Seq=\"1\" Entry=\"أَنَا\" Affix=\"هسته\" Pos=\"اسم\" Case=\"مبنی بر سکون\" Categ=\"تهی\" Def=\"معرفه\" Derv=\"\" DervT=\"ضمیر منفصل مرفوعی\" Gend=\"تهی\" Num=\"مفرد\" Root=\"تهی\" RootT=\"تهی\" Temp=\"تهی\" Varied=\"تهی\" Decl=\"\" Slice=\"أَنَا\" />","isNewWord":0},{"atrId":10,"delete":0,"id":112829,"idWord":82891,"nextId":112830,"prevId":112828,"Word":"أَعْلَمُ","xml":"<word Seq=\"1\" Slice=\"أَعْلَمُ\" Entry=\"أَعْلَمُ\" Affix=\"هسته\" Pos=\"اسم\" Case=\"مرفوع\" Categ=\"فَعِلَ یَفْعَلُ\" Def=\"نکره\" Derv=\"\" DervT=\"اسم تفضیل\" Gend=\"مذکر\" Num=\"مفرد\" Root=\"علم\" RootT=\"سالم\" Temp=\"أَفْعَلُ\" Varied=\"غیر منصرف\" Decl=\"\" />","isNewWord":0},{"atrId":41,"delete":0,"id":112830,"idWord":82892,"nextId":112831,"prevId":112829,"Word":"بِ","xml":"<word Seq=\"1\" Slice=\"بِ\" Entry=\"بِ\" Affix=\"هسته\" Pos=\"حرف\" Case=\"مبنی بر کسر\" Kol=\"جاره\" />","isNewWord":0},{"atrId":26,"delete":0,"id":112831,"idWord":82892,"nextId":112832,"prevId":112830,"Word":"مَا","xml":"<word Seq=\"2\" Slice=\"مَا\" Entry=\"مَا\" Affix=\"هسته\" Pos=\"اسم\" Case=\"مبنی بر سکون\" Categ=\"تهی\" Def=\"معرفه\" DervT=\"اسم موصول\" Gend=\"تهی\" Num=\"مشترک\" Root=\"تهی\" RootT=\"تهی\" Temp=\"تهی\" Varied=\"تهی\" />","isNewWord":0},{"atrId":1,"delete":0,"id":112832,"idWord":82893,"nextId":152567,"prevId":112831,"Word":"أَخْفَی","xml":"<word Seq=\"1\" Slice=\"أَخْفَی\" Entry=\"أَخْفَی\" Affix=\"هسته\" Pos=\"فعل\" Case=\"مبنی بر سکون\" Categ=\"افعال\" Gend=\"مذکر\" Num=\"جمع\" Root=\"خفی\" RootT=\"ناقص یائی\" Temp=\"أَفْعَلْتُمْ\" Time=\"ماضی\" TOV=\"9\" Trans=\"متعدی\" Voic=\"معلوم\" />","isNewWord":0},{"atrId":52,"delete":0,"id":112833,"idWord":82894,"nextId":112834,"prevId":152567,"Word":"وَ","xml":"<word Seq=\"1\" Slice=\"وَ\" Entry=\"وَ\" Affix=\"هسته\" Pos=\"حرف\" Lemma=\"وَ\" Case=\"مبنی بر فتح\" Kol=\"عاطفه\" Desc=\"\" />","isNewWord":0},{"atrId":26,"delete":0,"id":112834,"idWord":82895,"nextId":112835,"prevId":112833,"Word":"مَا","xml":"<word Seq=\"1\" Slice=\"مَا\" Entry=\"مَا\" Affix=\"هسته\" Pos=\"اسم\" Case=\"مبنی بر سکون\" Categ=\"تهی\" Def=\"معرفه\" Derv=\"\" DervT=\"اسم موصول\" Gend=\"تهی\" Num=\"مشترک\" Root=\"تهی\" RootT=\"تهی\" Temp=\"تهی\" Varied=\"تهی\" Decl=\"\" />","isNewWord":0},{"atrId":3,"delete":0,"id":112835,"idWord":82896,"nextId":152568,"prevId":112834,"Word":"أَعْلَن","xml":"<word Seq=\"1\" Slice=\"أَعْلَن\" Entry=\"أَعْلَن\" Affix=\"هسته\" Pos=\"فعل\" Case=\"مبنی بر سکون\" Categ=\"افعال\" Gend=\"مذکر\" Num=\"جمع\" Root=\"علن\" RootT=\"سالم\" Temp=\"أَفْعَلْتُمْ\" Time=\"ماضی\" TOV=\"9\" Trans=\"متعدی\" Voic=\"معلوم\" />","isNewWord":0},{"atrId":33,"delete":0,"id":112836,"idWord":82897,"nextId":112837,"prevId":152568,"Word":"وَ","xml":"<word Seq=\"1\" Slice=\"وَ\" Entry=\"وَ\" Affix=\"هسته\" Pos=\"حرف\" Lemma=\"وَ\" Case=\"مبنی بر فتح\" Kol=\"استینافیه\" Desc=\"\" />","isNewWord":0},{"atrId":14,"delete":0,"id":112837,"idWord":82898,"nextId":112838,"prevId":112836,"Word":"مَنْ","xml":"<word Seq=\"1\" Entry=\"مَنْ\" Affix=\"هسته\" Pos=\"اسم\" Case=\"مبنی بر سکون\" Categ=\"تهی\" Def=\"تهی\" Derv=\"\" DervT=\"اسم شرط\" Gend=\"تهی\" Num=\"تهی\" Root=\"تهی\" RootT=\"تهی\" Temp=\"تهی\" Varied=\"تهی\" Decl=\"\" Slice=\"مَنْ\" />","isNewWord":0},{"atrId":3,"delete":0,"id":112838,"idWord":82899,"nextId":158432,"prevId":112837,"Word":"یَفْعَلْ","xml":"<word Seq=\"1\" Slice=\"یَفْعَلْ\" Entry=\"یَفْعَلْ\" Affix=\"هسته\" Pos=\"فعل\" Case=\"مجزوم\" Categ=\"فَعَلَ یَفْعَلُ\" Gend=\"مذکر\" Num=\"مفرد\" Root=\"فعل\" RootT=\"سالم\" Temp=\"یَفْعَلْ\" Time=\"مضارع ساده\" TOV=\"1\" Trans=\"متعدی\" Voic=\"معلوم\" />","isNewWord":0},{"atrId":69,"delete":0,"id":112839,"idWord":82899,"nextId":112840,"prevId":158433,"Word":"هُ","xml":"<word Seq=\"2\" Slice=\"هُ\" Entry=\"هُ\" Affix=\"پسوند\" Pos=\"اسم\" Case=\"مبنی بر ضم\" Categ=\"تهی\" Def=\"معرفه\" Derv=\"\" DervT=\"ضمیر متصل منصوبی مجروری\" Gend=\"مذکر\" Num=\"مفرد\" Root=\"تهی\" RootT=\"تهی\" Temp=\"تهی\" Varied=\"تهی\" Decl=\"\" />","isNewWord":0},{"atrId":41,"delete":0,"id":112840,"idWord":82900,"nextId":112841,"prevId":112839,"Word":"مِنْ","xml":"<word Seq=\"1\" Entry=\"مِنْ\" Affix=\"پیشوند\" Pos=\"حرف\" Case=\"مبنی بر سکون\" Kol=\"جاره\" Slice=\"مِنْ\" />","isNewWord":0},{"atrId":71,"delete":0,"id":112841,"idWord":82900,"nextId":112842,"prevId":112840,"Word":"کُمْ","xml":"<word Seq=\"2\" Entry=\"كُمْ\" Affix=\"هسته\" Pos=\"اسم\" Case=\"مبنی بر سکون\" Categ=\"تهی\" Def=\"معرفه\" Derv=\"\" DervT=\"ضمیر متصل منصوبی مجروری\" Gend=\"مذکر\" Num=\"جمع\" Root=\"تهی\" RootT=\"تهی\" Temp=\"تهی\" Varied=\"تهی\" Decl=\"\" Slice=\"کُمْ\" />","isNewWord":0},{"atrId":45,"delete":0,"id":112842,"idWord":82901,"nextId":112843,"prevId":112841,"Word":"فَ","xml":"<word Seq=\"1\" Slice=\"فَ\" Entry=\"فَ\" Affix=\"پیشوند\" Pos=\"حرف\" Case=\"مبنی بر فتح\" Kol=\"جواب\" />","isNewWord":0},{"atrId":36,"delete":0,"id":112843,"idWord":82901,"nextId":112844,"prevId":112842,"Word":"قَدْ","xml":"<word Seq=\"2\" Slice=\"قَدْ\" Entry=\"قَدْ\" Affix=\"هسته\" Pos=\"حرف\" Case=\"مبنی بر سکون\" Kol=\"تحقیقیه\" />","isNewWord":0},{"atrId":1,"delete":0,"id":112844,"idWord":82902,"nextId":135680,"prevId":112843,"Word":"ضَلَّ","xml":"<word Seq=\"1\" Slice=\"ضَلَّ\" Entry=\"ضَلَّ\" Affix=\"هسته\" Pos=\"فعل\" Case=\"مبنی بر فتح\" Categ=\"فَعَلَ یَفْعِلُ\" Gend=\"مذکر\" Num=\"مفرد\" Root=\"ضلل\" RootT=\"مضاعف\" Temp=\"فَعَلَ\" Time=\"ماضی\" TOV=\"1\" Trans=\"لازم\" Voic=\"معلوم\" />","isNewWord":0},{"atrId":4,"delete":0,"id":112845,"idWord":82903,"nextId":112846,"prevId":135680,"Word":"سَوَاءَ","xml":"<word Seq=\"1\" Slice=\"سَوَاءَ\" Entry=\"سَوَاءَ\" Affix=\"هسته\" Pos=\"اسم\" Case=\"منصوب\" Categ=\"ثلاثی مجرد\" Def=\"اضافه\" DervT=\"جامد غیر مصدری\" Gend=\"مذکر\" Num=\"مفرد\" Root=\"سوو\" RootT=\"لفیف مقرون\" Temp=\"فَعْلَاءَ\" Varied=\"منصرف\" />","isNewWord":0},{"atrId":37,"delete":0,"id":112846,"idWord":82904,"nextId":112847,"prevId":112845,"Word":"ال","xml":"<word Seq=\"1\" Slice=\"ال\" Entry=\"الْ\" Affix=\"پیشوند\" Pos=\"حرف\" Case=\"مبنی بر سکون\" Kol=\"تعریف\" />","isNewWord":0},{"atrId":4,"delete":0,"id":112847,"idWord":82904,"nextId":null,"prevId":112846,"Word":"سَّبِیلِ","xml":"<word Seq=\"2\" Slice=\"سَّبِیلِ\" Entry=\"سَبِیلِ\" Affix=\"هسته\" Pos=\"اسم\" Case=\"مجرور\" Categ=\"ثلاثی مجرد\" Def=\"معرفه\" Derv=\"\" DervT=\"جامد غیر مصدری\" Gend=\"مذکر\" Num=\"مفرد\" Root=\"سبل\" RootT=\"سالم\" Temp=\"فَعِیلِ\" Varied=\"منصرف\" Decl=\"\" />","isNewWord":0},{"atrId":76,"delete":0,"id":135673,"idWord":102821,"nextId":112796,"prevId":112795,"Word":"*","xml":null,"isNewWord":1},{"atrId":76,"delete":0,"id":135680,"idWord":102828,"nextId":112845,"prevId":112844,"Word":"هو","xml":null,"isNewWord":1},{"atrId":72,"delete":0,"id":152551,"idWord":82852,"nextId":152552,"prevId":112774,"Word":"ُو","xml":"<word Seq=\"2\" Entry=\"ُو\" Affix=\"پسوند\" Pos=\"اسم\" Case=\"مبنی بر سکون\" Categ=\"تهی\" Def=\"معرفه\" Derv=\"\" DervT=\"ضمیر متصل مرفوعی\" Gend=\"مذکر\" Num=\"جمع\" Root=\"تهی\" RootT=\"تهی\" Temp=\"تهی\" Varied=\"تهی\" Decl=\"\" Slice=\"ُو\" />","isNewWord":0},{"atrId":73,"delete":0,"id":152552,"idWord":82852,"nextId":112775,"prevId":152551,"Word":"ا","xml":"<word Seq=\"3\" Entry=\"ا\" Affix=\"پسوند\" Pos=\"حرف\" Case=\"مبنی بر سکون\" Kol=\"الف زینت\" Slice=\"ا\" />","isNewWord":0},{"atrId":72,"delete":0,"id":152553,"idWord":82854,"nextId":152554,"prevId":112776,"Word":"ُو","xml":"<word Seq=\"2\" Slice=\"ُو\" Entry=\"ُو\" Affix=\"پسوند\" Pos=\"اسم\" Case=\"مبنی بر سکون\" Categ=\"تهی\" Def=\"معرفه\" Derv=\"\" DervT=\"ضمیر متصل مرفوعی\" Gend=\"مذکر\" Num=\"جمع\" Root=\"تهی\" RootT=\"تهی\" Temp=\"تهی\" Varied=\"تهی\" Decl=\"\" />","isNewWord":0},{"atrId":73,"delete":0,"id":152554,"idWord":82854,"nextId":112777,"prevId":152553,"Word":"ا","xml":"<word Seq=\"3\" Slice=\"ا\" Entry=\"ا\" Affix=\"پسوند\" Pos=\"حرف\" Case=\"مبنی بر سکون\" Kol=\"الف زینت\" />","isNewWord":0},{"atrId":72,"delete":0,"id":152555,"idWord":82859,"nextId":152556,"prevId":112783,"Word":"ُو","xml":"<word Seq=\"2\" Slice=\"ُو\" Entry=\"ُو\" Affix=\"پسوند\" Pos=\"اسم\" Case=\"مبنی بر سکون\" Categ=\"تهی\" Def=\"معرفه\" DervT=\"ضمیر متصل مرفوعی\" Gend=\"مذکر\" Num=\"جمع\" Root=\"تهی\" RootT=\"تهی\" Temp=\"تهی\" Varied=\"تهی\" />","isNewWord":0},{"atrId":74,"delete":0,"id":152556,"idWord":82859,"nextId":112784,"prevId":152555,"Word":"نَ","xml":"<word Seq=\"3\" Slice=\"نَ\" Entry=\"نَ\" Affix=\"پسوند\" Pos=\"حرف\" Case=\"مبنی بر فتح\" Kol=\"نون عوض رفع\" />","isNewWord":0},{"atrId":72,"delete":0,"id":152557,"idWord":82864,"nextId":152558,"prevId":112791,"Word":"ُو","xml":"<word Seq=\"2\" Entry=\"ُو\" Affix=\"پسوند\" Pos=\"اسم\" Case=\"مبنی بر سکون\" Categ=\"تهی\" Def=\"معرفه\" Derv=\"\" DervT=\"ضمیر متصل مرفوعی\" Gend=\"مذکر\" Num=\"جمع\" Root=\"تهی\" RootT=\"تهی\" Temp=\"تهی\" Varied=\"تهی\" Decl=\"\" Slice=\"ُو\" />","isNewWord":0},{"atrId":73,"delete":0,"id":152558,"idWord":82864,"nextId":112792,"prevId":152557,"Word":"ا","xml":"<word Seq=\"3\" Entry=\"ا\" Affix=\"پسوند\" Pos=\"حرف\" Case=\"مبنی بر سکون\" Kol=\"الف زینت\" Slice=\"ا\" />","isNewWord":0},{"atrId":72,"delete":0,"id":152559,"idWord":82869,"nextId":152560,"prevId":112799,"Word":"ُو","xml":"<word Seq=\"2\" Slice=\"ُو\" Entry=\"ُو\" Affix=\"پسوند\" Pos=\"اسم\" Case=\"مبنی بر سکون\" Categ=\"تهی\" Def=\"معرفه\" Derv=\"\" DervT=\"ضمیر متصل مرفوعی\" Gend=\"مذکر\" Num=\"جمع\" Root=\"تهی\" RootT=\"تهی\" Temp=\"تهی\" Varied=\"تهی\" Decl=\"\" />","isNewWord":0},{"atrId":74,"delete":0,"id":152560,"idWord":82869,"nextId":112800,"prevId":152559,"Word":"نَ","xml":"<word Seq=\"3\" Slice=\"نَ\" Entry=\"نَ\" Affix=\"پسوند\" Pos=\"حرف\" Case=\"مبنی بر فتح\" Kol=\"نون عوض رفع\" />","isNewWord":0},{"atrId":72,"delete":0,"id":152561,"idWord":82874,"nextId":152562,"prevId":112805,"Word":"ُو","xml":"<word Seq=\"2\" Slice=\"ُو\" Entry=\"ُو\" Affix=\"پسوند\" Pos=\"اسم\" Case=\"مبنی بر سکون\" Categ=\"تهی\" Def=\"معرفه\" Derv=\"\" DervT=\"ضمیر متصل مرفوعی\" Gend=\"مذکر\" Num=\"جمع\" Root=\"تهی\" RootT=\"تهی\" Temp=\"تهی\" Varied=\"تهی\" Decl=\"\" />","isNewWord":0},{"atrId":73,"delete":0,"id":152562,"idWord":82874,"nextId":112806,"prevId":152561,"Word":"ا","xml":"<word Seq=\"3\" Slice=\"ا\" Entry=\"ا\" Affix=\"پسوند\" Pos=\"حرف\" Case=\"مبنی بر سکون\" Kol=\"الف زینت\" />","isNewWord":0},{"atrId":72,"delete":0,"id":152563,"idWord":82878,"nextId":112812,"prevId":112811,"Word":"ْتُمْ","xml":"<word Seq=\"2\" Entry=\"تُمْ\" Affix=\"پسوند\" Pos=\"اسم\" Case=\"مبنی بر سکون\" Categ=\"تهی\" Def=\"معرفه\" Derv=\"\" DervT=\"ضمیر متصل مرفوعی\" Gend=\"مذکر\" Num=\"جمع\" Root=\"تهی\" RootT=\"تهی\" Temp=\"تهی\" Varied=\"تهی\" Decl=\"\" Slice=\"ْتُمْ\" />","isNewWord":0},{"atrId":72,"delete":0,"id":152564,"idWord":82879,"nextId":112813,"prevId":112812,"Word":"ْتُمْ","xml":"<word Seq=\"2\" Slice=\"ْتُمْ\" Entry=\"تُمْ\" Affix=\"پسوند\" Pos=\"اسم\" Case=\"مبنی بر سکون\" Categ=\"تهی\" Def=\"معرفه\" Derv=\"\" DervT=\"ضمیر متصل مرفوعی\" Gend=\"مذکر\" Num=\"جمع\" Root=\"تهی\" RootT=\"تهی\" Temp=\"تهی\" Varied=\"تهی\" Decl=\"\" />","isNewWord":0},{"atrId":72,"delete":0,"id":152565,"idWord":82886,"nextId":152566,"prevId":112821,"Word":"ُو","xml":"<word Seq=\"2\" Slice=\"ُو\" Entry=\"ُو\" Affix=\"پسوند\" Pos=\"اسم\" Case=\"مبنی بر سکون\" Categ=\"تهی\" Def=\"معرفه\" Derv=\"\" DervT=\"ضمیر متصل مرفوعی\" Gend=\"مذکر\" Num=\"جمع\" Root=\"تهی\" RootT=\"تهی\" Temp=\"تهی\" Varied=\"تهی\" Decl=\"\" />","isNewWord":0},{"atrId":74,"delete":0,"id":152566,"idWord":82886,"nextId":112822,"prevId":152565,"Word":"نَ","xml":"<word Seq=\"3\" Slice=\"نَ\" Entry=\"نَ\" Affix=\"پسوند\" Pos=\"حرف\" Case=\"مبنی بر فتح\" Kol=\"نون عوض رفع\" />","isNewWord":0},{"atrId":72,"delete":0,"id":152567,"idWord":82893,"nextId":112833,"prevId":112832,"Word":"ْتُمْ","xml":"<word Seq=\"2\" Slice=\"ْتُمْ\" Entry=\"تُمْ\" Affix=\"پسوند\" Pos=\"اسم\" Case=\"مبنی بر سکون\" Categ=\"تهی\" Def=\"معرفه\" DervT=\"ضمیر متصل مرفوعی\" Gend=\"مذکر\" Num=\"جمع\" Root=\"تهی\" RootT=\"تهی\" Temp=\"تهی\" Varied=\"تهی\" />","isNewWord":0},{"atrId":72,"delete":0,"id":152568,"idWord":82896,"nextId":112836,"prevId":112835,"Word":"ْتُمْ","xml":"<word Seq=\"2\" Slice=\"ْتُمْ\" Entry=\"تُمْ\" Affix=\"پسوند\" Pos=\"اسم\" Case=\"مبنی بر سکون\" Categ=\"تهی\" Def=\"معرفه\" DervT=\"ضمیر متصل مرفوعی\" Gend=\"مذکر\" Num=\"جمع\" Root=\"تهی\" RootT=\"تهی\" Temp=\"تهی\" Varied=\"تهی\" />","isNewWord":0},{"atrId":76,"delete":0,"id":155685,"idWord":88454,"nextId":112795,"prevId":112794,"Word":"هو","xml":null,"isNewWord":1},{"atrId":76,"delete":0,"id":158432,"idWord":158432,"nextId":158433,"prevId":112838,"Word":"هو","xml":null,"isNewWord":1},{"atrId":76,"delete":0,"id":158433,"idWord":158433,"nextId":112839,"prevId":158432,"Word":"*","xml":null,"isNewWord":1}],"TotalCount":101,"Id":"0","IsSuccess":true,"Message":"OK","StatusCode":200,"ValidationMessages":null,"Exception":null,"ResponseTime":"2020-12-02T12:14:58.4929561Z"},"edge":{"Data":[{"arrow":"LTR","ayehId":1,"from":112771,"to":112770,"id":135629,"relationId":24,"word1":"أَیُّ","word2":"يَا","idRun":112771},{"arrow":"LTR","ayehId":1,"from":112772,"to":112771,"id":183333,"relationId":44,"word1":"هَا","word2":"أَیُّ","idRun":112772},{"arrow":"LTR","ayehId":1,"from":112773,"to":112771,"id":135693,"relationId":9,"word1":"الَّذِينَ ","word2":"أَیُّ","idRun":112773},{"arrow":"LTR","ayehId":1,"from":112774,"to":112773,"id":135632,"relationId":15,"word1":"آمَن","word2":"الَّذِينَ ","idRun":112774},{"arrow":"LTR","ayehId":1,"from":112775,"to":112770,"id":180143,"relationId":27,"word1":"لَا","word2":"يَا","idRun":112775},{"arrow":"LTR","ayehId":1,"from":112776,"to":112775,"id":135703,"relationId":40,"word1":"تَتَّخِذ","word2":"لَا","idRun":112776},{"arrow":"LTR","ayehId":1,"from":112777,"to":112776,"id":135706,"relationId":4,"word1":"عَدُوِّ","word2":"تَتَّخِذ","idRun":112777},{"arrow":"LTR","ayehId":1,"from":112778,"to":112777,"id":135642,"relationId":6,"word1":"ی","word2":"عَدُوِّ","idRun":112778},{"arrow":"LTR","ayehId":1,"from":112779,"to":112777,"id":142959,"relationId":11,"word1":"وَ","word2":"عَدُوِّ","idRun":112779},{"arrow":"LTR","ayehId":1,"from":112780,"to":112779,"id":142958,"relationId":55,"word1":"عَدُوَّ","word2":"وَ","idRun":112780},{"arrow":"LTR","ayehId":1,"from":112781,"to":112780,"id":135643,"relationId":6,"word1":"کُمْ","word2":"عَدُوَّ","idRun":112781},{"arrow":"LTR","ayehId":1,"from":112782,"to":112776,"id":135707,"relationId":4,"word1":"أَوْلِيَاءَ","word2":"تَتَّخِذ","idRun":112782},{"arrow":"LTR","ayehId":1,"from":112783,"to":112776,"id":135708,"relationId":7,"word1":"تُلْق","word2":"تَتَّخِذ","idRun":112783},{"arrow":"LTR","ayehId":1,"from":112784,"to":112783,"id":135649,"relationId":13,"word1":"إِلَیْ","word2":"تُلْق","idRun":112784},{"arrow":"LTR","ayehId":1,"from":112785,"to":112784,"id":135648,"relationId":5,"word1":"هِمْ","word2":"إِلَیْ","idRun":112785},{"arrow":"LTR","ayehId":1,"from":112786,"to":112783,"id":135709,"relationId":13,"word1":"بِ","word2":"تُلْق","idRun":112786},{"arrow":"LTR","ayehId":1,"from":112788,"to":112786,"id":135651,"relationId":5,"word1":"مَوَدَّةِ","word2":"بِ","idRun":112788},{"arrow":"RTL","ayehId":1,"from":112788,"to":112787,"id":50331,"relationId":29,"word1":"مَوَدَّةِ","word2":"الْ","idRun":112788},{"arrow":"LTR","ayehId":1,"from":112789,"to":112776,"id":180145,"relationId":7,"word1":"وَ","word2":"تَتَّخِذ","idRun":112789},{"arrow":"LTR","ayehId":1,"from":112790,"to":112789,"id":180144,"relationId":61,"word1":"قَدْ","word2":"وَ","idRun":112790},{"arrow":"LTR","ayehId":1,"from":112791,"to":112790,"id":135711,"relationId":36,"word1":"کَفَر","word2":"قَدْ","idRun":112791},{"arrow":"LTR","ayehId":1,"from":112792,"to":112791,"id":135652,"relationId":13,"word1":"بِ","word2":"کَفَر","idRun":112792},{"arrow":"LTR","ayehId":1,"from":112793,"to":112792,"id":135714,"relationId":5,"word1":"مَا","word2":"بِ","idRun":112793},{"arrow":"LTR","ayehId":1,"from":112794,"to":112793,"id":135715,"relationId":15,"word1":"جَاءَ","word2":"مَا","idRun":112794},{"arrow":"LTR","ayehId":1,"from":112795,"to":112794,"id":135653,"relationId":4,"word1":"کُمْ","word2":"جَاءَ","idRun":112795},{"arrow":"LTR","ayehId":1,"from":112798,"to":112796,"id":135654,"relationId":5,"word1":"حَقِّ","word2":"مِنَ","idRun":112798},{"arrow":"RTL","ayehId":1,"from":112798,"to":112797,"id":50330,"relationId":29,"word1":"حَقِّ","word2":"الْ","idRun":112798},{"arrow":"LTR","ayehId":1,"from":112799,"to":112791,"id":135744,"relationId":7,"word1":"یُخْرِج","word2":"کَفَر","idRun":112799},{"arrow":"LTR","ayehId":1,"from":112801,"to":112799,"id":135655,"relationId":4,"word1":"رَّسُولَ","word2":"یُخْرِج","idRun":112801},{"arrow":"RTL","ayehId":1,"from":112801,"to":112800,"id":50329,"relationId":29,"word1":"رَّسُولَ","word2":"ال","idRun":112801},{"arrow":"LTR","ayehId":1,"from":112802,"to":112801,"id":140755,"relationId":11,"word1":"وَ","word2":"رَّسُولَ","idRun":112802},{"arrow":"LTR","ayehId":1,"from":112803,"to":112802,"id":140754,"relationId":55,"word1":"إِيَّاكُمْ","word2":"وَ","idRun":112803},{"arrow":"LTR","ayehId":1,"from":112804,"to":112799,"id":180146,"relationId":23,"word1":"أَنْ","word2":"یُخْرِج","idRun":112804},{"arrow":"LTR","ayehId":1,"from":112805,"to":112804,"id":135741,"relationId":59,"word1":"تُؤْمِن","word2":"أَنْ","idRun":112805},{"arrow":"LTR","ayehId":1,"from":112806,"to":112805,"id":135659,"relationId":13,"word1":"بِ","word2":"تُؤْمِن","idRun":112806},{"arrow":"LTR","ayehId":1,"from":112807,"to":112806,"id":135657,"relationId":5,"word1":"اللَّهِ","word2":"بِ","idRun":112807},{"arrow":"LTR","ayehId":1,"from":112808,"to":112807,"id":135743,"relationId":9,"word1":"رَبِّ","word2":"اللَّهِ","idRun":112808},{"arrow":"LTR","ayehId":1,"from":112809,"to":112808,"id":135661,"relationId":6,"word1":"کُمْ","word2":"رَبِّ","idRun":112809},{"arrow":"LTR","ayehId":1,"from":112811,"to":112810,"id":135662,"relationId":21,"word1":"کُن","word2":"إِنْ","idRun":112811},{"arrow":"LTR","ayehId":1,"from":112812,"to":112811,"id":135745,"relationId":3,"word1":"خَرَج","word2":"کُن","idRun":112812},{"arrow":"LTR","ayehId":1,"from":112813,"to":112812,"id":135747,"relationId":23,"word1":"جِهَادًا","word2":"خَرَج","idRun":112813},{"arrow":"LTR","ayehId":1,"from":112814,"to":112813,"id":135749,"relationId":13,"word1":"فِي","word2":"جِهَادًا","idRun":112814},{"arrow":"LTR","ayehId":1,"from":112815,"to":112814,"id":135665,"relationId":5,"word1":"سَبِیلِ","word2":"فِي","idRun":112815},{"arrow":"LTR","ayehId":1,"from":112816,"to":112815,"id":135666,"relationId":6,"word1":"ی","word2":"سَبِیلِ","idRun":112816},{"arrow":"LTR","ayehId":1,"from":112817,"to":112813,"id":144979,"relationId":11,"word1":"وَ","word2":"جِهَادًا","idRun":112817},{"arrow":"LTR","ayehId":1,"from":112818,"to":112817,"id":144978,"relationId":55,"word1":"اِبْتِغَاءَ","word2":"وَ","idRun":112818},{"arrow":"LTR","ayehId":1,"from":112819,"to":112818,"id":135669,"relationId":6,"word1":"مَرْضَاتِ","word2":"اِبْتِغَاءَ","idRun":112819},{"arrow":"LTR","ayehId":1,"from":112820,"to":112819,"id":135670,"relationId":6,"word1":"ی","word2":"مَرْضَاتِ","idRun":112820},{"arrow":"LTR","ayehId":1,"from":112822,"to":112821,"id":135671,"relationId":13,"word1":"إِلَیْ","word2":"تُسِرّ","idRun":112822},{"arrow":"LTR","ayehId":1,"from":112823,"to":112822,"id":135672,"relationId":5,"word1":"هِمْ","word2":"إِلَیْ","idRun":112823},{"arrow":"LTR","ayehId":1,"from":112824,"to":112821,"id":135751,"relationId":13,"word1":"بِ","word2":"تُسِرّ","idRun":112824},{"arrow":"LTR","ayehId":1,"from":112826,"to":112824,"id":135673,"relationId":5,"word1":"مَوَدَّةِ","word2":"بِ","idRun":112826},{"arrow":"RTL","ayehId":1,"from":112826,"to":112825,"id":50328,"relationId":29,"word1":"مَوَدَّةِ","word2":"الْ","idRun":112826},{"arrow":"LTR","ayehId":1,"from":112827,"to":112821,"id":180149,"relationId":7,"word1":"وَ","word2":"تُسِرّ","idRun":112827},{"arrow":"LTR","ayehId":1,"from":112828,"to":112827,"id":180150,"relationId":61,"word1":"أَنَا","word2":"وَ","idRun":112828},{"arrow":"LTR","ayehId":1,"from":112829,"to":112828,"id":135674,"relationId":3,"word1":"أَعْلَمُ","word2":"أَنَا","idRun":112829},{"arrow":"LTR","ayehId":1,"from":112830,"to":112829,"id":135675,"relationId":13,"word1":"بِ","word2":"أَعْلَمُ","idRun":112830},{"arrow":"LTR","ayehId":1,"from":112831,"to":112830,"id":135676,"relationId":5,"word1":"مَا","word2":"بِ","idRun":112831},{"arrow":"LTR","ayehId":1,"from":112832,"to":112831,"id":135677,"relationId":15,"word1":"أَخْفَی","word2":"مَا","idRun":112832},{"arrow":"LTR","ayehId":1,"from":112833,"to":112831,"id":142961,"relationId":11,"word1":"وَ","word2":"مَا","idRun":112833},{"arrow":"LTR","ayehId":1,"from":112834,"to":112833,"id":142960,"relationId":55,"word1":"مَا","word2":"وَ","idRun":112834},{"arrow":"LTR","ayehId":1,"from":112835,"to":112834,"id":135753,"relationId":15,"word1":"أَعْلَن","word2":"مَا","idRun":112835},{"arrow":"LTR","ayehId":1,"from":112837,"to":112836,"id":180151,"relationId":48,"word1":"مَنْ","word2":"وَ","idRun":112837},{"arrow":"LTR","ayehId":1,"from":112838,"to":112837,"id":135762,"relationId":21,"word1":"یَفْعَلْ","word2":"مَنْ","idRun":112838},{"arrow":"LTR","ayehId":1,"from":112838,"to":112837,"id":135763,"relationId":3,"word1":"یَفْعَلْ","word2":"مَنْ","idRun":112838},{"arrow":"LTR","ayehId":1,"from":112838,"to":158432,"id":234181,"relationId":1,"word1":"یَفْعَلْ","word2":"هو","idRun":112838},{"arrow":"LTR","ayehId":1,"from":112839,"to":112838,"id":135678,"relationId":4,"word1":"هُ","word2":"یَفْعَلْ","idRun":112839},{"arrow":"LTR","ayehId":1,"from":112841,"to":112840,"id":135680,"relationId":5,"word1":"کُمْ","word2":"مِنْ","idRun":112841},{"arrow":"LTR","ayehId":1,"from":112842,"to":112837,"id":180147,"relationId":22,"word1":"فَ","word2":"مَنْ","idRun":112842},{"arrow":"LTR","ayehId":1,"from":112843,"to":112842,"id":180148,"relationId":52,"word1":"قَدْ","word2":"فَ","idRun":112843},{"arrow":"LTR","ayehId":1,"from":112844,"to":112843,"id":135765,"relationId":36,"word1":"ضَلَّ","word2":"قَدْ","idRun":112844},{"arrow":"LTR","ayehId":1,"from":112845,"to":112844,"id":135768,"relationId":4,"word1":"سَوَاءَ","word2":"ضَلَّ","idRun":112845},{"arrow":"LTR","ayehId":1,"from":112847,"to":112845,"id":135766,"relationId":6,"word1":"سَّبِیلِ","word2":"سَوَاءَ","idRun":112847},{"arrow":"RTL","ayehId":1,"from":112847,"to":112846,"id":50327,"relationId":29,"word1":"سَّبِیلِ","word2":"ال","idRun":112847},{"arrow":"LTR","ayehId":1,"from":135673,"to":112796,"id":135716,"relationId":13,"word1":"*","word2":"مِنَ","idRun":135673},{"arrow":"LTR","ayehId":1,"from":135680,"to":112844,"id":135769,"relationId":1,"word1":"هو","word2":"ضَلَّ","idRun":135680},{"arrow":"LTR","ayehId":1,"from":152551,"to":112774,"id":234185,"relationId":1,"word1":"ُو","word2":"آمَن","idRun":152551},{"arrow":"LTR","ayehId":1,"from":152552,"to":112774,"id":209988,"relationId":63,"word1":"ا","word2":"آمَن","idRun":152552},{"arrow":"LTR","ayehId":1,"from":152553,"to":112776,"id":234186,"relationId":1,"word1":"ُو","word2":"تَتَّخِذ","idRun":152553},{"arrow":"LTR","ayehId":1,"from":152554,"to":112776,"id":209989,"relationId":63,"word1":"ا","word2":"تَتَّخِذ","idRun":152554},{"arrow":"LTR","ayehId":1,"from":152555,"to":112783,"id":234188,"relationId":1,"word1":"ُو","word2":"تُلْق","idRun":152555},{"arrow":"LTR","ayehId":1,"from":152556,"to":112783,"id":234187,"relationId":64,"word1":"نَ","word2":"تُلْق","idRun":152556},{"arrow":"LTR","ayehId":1,"from":152557,"to":112791,"id":234182,"relationId":1,"word1":"ُو","word2":"کَفَر","idRun":152557},{"arrow":"LTR","ayehId":1,"from":152558,"to":112791,"id":209990,"relationId":63,"word1":"ا","word2":"کَفَر","idRun":152558},{"arrow":"LTR","ayehId":1,"from":152559,"to":112799,"id":234177,"relationId":1,"word1":"ُو","word2":"یُخْرِج","idRun":152559},{"arrow":"LTR","ayehId":1,"from":152560,"to":112799,"id":234176,"relationId":64,"word1":"نَ","word2":"یُخْرِج","idRun":152560},{"arrow":"LTR","ayehId":1,"from":152561,"to":112805,"id":234178,"relationId":1,"word1":"ُو","word2":"تُؤْمِن","idRun":152561},{"arrow":"LTR","ayehId":1,"from":152562,"to":112805,"id":209991,"relationId":63,"word1":"ا","word2":"تُؤْمِن","idRun":152562},{"arrow":"LTR","ayehId":1,"from":152563,"to":112811,"id":206125,"relationId":14,"word1":"ْتُمْ","word2":"کُن","idRun":152563},{"arrow":"LTR","ayehId":1,"from":152564,"to":112812,"id":206126,"relationId":1,"word1":"ْتُمْ","word2":"خَرَج","idRun":152564},{"arrow":"LTR","ayehId":1,"from":152565,"to":112821,"id":234180,"relationId":1,"word1":"ُو","word2":"تُسِرّ","idRun":152565},{"arrow":"LTR","ayehId":1,"from":152566,"to":112821,"id":234179,"relationId":64,"word1":"نَ","word2":"تُسِرّ","idRun":152566},{"arrow":"LTR","ayehId":1,"from":152567,"to":112832,"id":206128,"relationId":1,"word1":"ْتُمْ","word2":"أَخْفَی","idRun":152567},{"arrow":"LTR","ayehId":1,"from":152568,"to":112835,"id":206129,"relationId":1,"word1":"ْتُمْ","word2":"أَعْلَن","idRun":152568},{"arrow":"LTR","ayehId":1,"from":155685,"to":112794,"id":221524,"relationId":1,"word1":"هو","word2":"جَاءَ","idRun":155685},{"arrow":"LTR","ayehId":1,"from":158432,"to":158433,"id":234184,"relationId":7,"word1":"هو","word2":"*","idRun":158432},{"arrow":"LTR","ayehId":1,"from":158433,"to":112840,"id":234183,"relationId":13,"word1":"*","word2":"مِنْ","idRun":158433}],"TotalCount":97,"Id":"0","IsSuccess":true,"Message":"OK","StatusCode":200,"ValidationMessages":null,"Exception":null,"ResponseTime":"2020-12-02T12:14:58.4929561Z"},"text":[{"Id":5209,"Number":1,"HasProstration":false,"PageNumber":549,"JuzNumber":28,"Text":"يَـٰٓأَيُّهَا ٱلَّذِينَ ءَامَنُواْ لَا تَتَّخِذُواْ عَدُوِّي وَعَدُوَّكُمۡ أَوۡلِيَآءَ تُلۡقُونَ إِلَيۡهِم بِٱلۡمَوَدَّةِ وَقَدۡ كَفَرُواْ بِمَا جَآءَكُم مِّنَ ٱلۡحَقِّ يُخۡرِجُونَ ٱلرَّسُولَ وَإِيَّاكُمۡ<em class=\"sajavandi-sign\">ۙ</em> أَن تُؤۡمِنُواْ بِٱللَّهِ رَبِّكُمۡ إِن كُنتُمۡ خَرَجۡتُمۡ جِهَٰدٗا فِي سَبِيلِي وَٱبۡتِغَآءَ مَرۡضَاتِي<em class=\"sajavandi-sign\">ۚ</em> تُسِرُّونَ إِلَيۡهِم بِٱلۡمَوَدَّةِ وَأَنَا۠ أَعۡلَمُ بِمَآ أَخۡفَيۡتُمۡ وَمَآ أَعۡلَنتُمۡ<em class=\"sajavandi-sign\">ۚ</em> وَمَن يَفۡعَلۡهُ مِنكُمۡ فَقَدۡ ضَلَّ سَوَآءَ ٱلسَّبِيلِ","SurahTitle":"الممتحنة","SurahId":60,"FileUrl":"/File/Sound/Recitation/1-AbdeAlrahmaanSudis/sudis060001.mp3","MaxAyahNumber":13,"MaxAyahNumberPrevSurah":24,"ResultCount":1}]}},"Id":null,"IsSuccess":true,"Message":null,"StatusCode":200,"ValidationMessages":null,"Exception":null,"ResponseTime":"2020-12-02T12:14:58.4917381Z"}